kontr_api/__init__.py
kontr_api/auth.py
kontr_api/client.py
kontr_api/errors.py
kontr_api/log_config.py
kontr_api/resources/__init__.py
kontr_api/resources/clients.py
kontr_api/resources/courses.py
kontr_api/resources/default.py
kontr_api/resources/groups.py
kontr_api/resources/mixins.py
kontr_api/resources/projects.py
kontr_api/resources/roles.py
kontr_api/resources/secrets.py
kontr_api/resources/submission_files.py
kontr_api/resources/submissions.py
kontr_api/resources/users.py
kontr_api/resources/workers.py
kontr_api/rest_client.py
kontr_api-0.2.0.dist-info/LICENSE
kontr_api-0.2.0.dist-info/WHEEL
kontr_api-0.2.0.dist-info/METADATA
kontr_api-0.2.0.dist-info/RECORD
