Metadata-Version: 2.1
Name: kontr-api
Version: 0.2.0
Summary: Kontr Portal REST Api Client
Home-page: https://gitlab.fi.muni.cz/grp-kontr2/kontr-api
License: Apache-2.0
Author: Peter Stanko
Author-email: stanko@mail.muni.cz
Requires-Python: >=3.6,<4.0
Classifier: License :: OSI Approved :: Apache Software License
Classifier: Programming Language :: Python :: 3
Classifier: Programming Language :: Python :: 3.10
Classifier: Programming Language :: Python :: 3.6
Classifier: Programming Language :: Python :: 3.7
Classifier: Programming Language :: Python :: 3.8
Classifier: Programming Language :: Python :: 3.9
Requires-Dist: pyjwt
Requires-Dist: requests
Project-URL: Documentation, https://gitlab.fi.muni.cz/grp-kontr2/kontr-api
Project-URL: Repository, https://gitlab.fi.muni.cz/grp-kontr2/kontr-api
